README.md
setup.py
fnshelp/__init__.py
fnshelp/ner.py
fnshelp.egg-info/PKG-INFO
fnshelp.egg-info/SOURCES.txt
fnshelp.egg-info/dependency_links.txt
fnshelp.egg-info/not-zip-safe
fnshelp.egg-info/top_level.txt