Metadata-Version: 1.0
Name: fnshelp
Version: 0.2.1.2
Summary: Repo for most used functions
Home-page: http://github.com/gitlost-murali/fnshelp
Author: Murali Kondragunta
Author-email: kmanoharmurali@gmail.com
License: MIT
Platform: UNKNOWN
